p1_ipc_tracker/pipeline.sv
// 5-Stage Pipelined CPU — IPC Tracker
module pipeline_cpu (
    input  logic        clk,
    input  logic        rst,
    input  logic [31:0] instruction,
    output logic [63:0] ipc_x100,
    output logic [63:0] total_instructions,
    output logic [63:0] total_cycles,
    output logic [63:0] stall_cycles
);

logic [31:0] IF_ID_instr, ID_EX_instr, EX_MEM_instr, MEM_WB_instr;
logic        IF_ID_valid, ID_EX_valid, EX_MEM_valid, MEM_WB_valid;
logic stall;
logic branch_taken;
logic [4:0]  rs1, rs2, rd_ex, rd_mem;
logic [2:0]  opcode;

assign opcode = IF_ID_instr[31:29];
assign rs1    = IF_ID_instr[28:24];
assign rs2    = IF_ID_instr[23:19];
assign rd_ex  = ID_EX_instr[18:14];
assign rd_mem = EX_MEM_instr[18:14];

assign stall = (ID_EX_valid  && rd_ex  != 0 && (rd_ex  == rs1 || rd_ex  == rs2)) ||
               (EX_MEM_valid && rd_mem != 0 && (rd_mem == rs1 || rd_mem == rs2));

assign branch_taken = (ID_EX_valid && ID_EX_instr[31:29] == 3'b110);

always_ff @(posedge clk or posedge rst) begin
    if (rst) begin
        IF_ID_instr  <= 32'b0; IF_ID_valid  <= 0;
        ID_EX_instr  <= 32'b0; ID_EX_valid  <= 0;
        EX_MEM_instr <= 32'b0; EX_MEM_valid <= 0;
        MEM_WB_instr <= 32'b0; MEM_WB_valid <= 0;
    end else begin
        if (!stall) begin
            IF_ID_instr <= (branch_taken) ? 32'b0 : instruction;
            IF_ID_valid <= !branch_taken;
        end
        ID_EX_instr  <= stall ? 32'b0 : IF_ID_instr;
        ID_EX_valid  <= stall ? 1'b0  : IF_ID_valid;
        EX_MEM_instr <= ID_EX_instr;
        EX_MEM_valid <= ID_EX_valid;
        MEM_WB_instr <= EX_MEM_instr;
        MEM_WB_valid <= EX_MEM_valid;
    end
end

always_ff @(posedge clk or posedge rst) begin
    if (rst) begin
        total_cycles       <= 0;
        total_instructions <= 0;
        stall_cycles       <= 0;
        ipc_x100           <= 0;
    end else begin
        total_cycles <= total_cycles + 1;
        if (stall)
            stall_cycles <= stall_cycles + 1;
        if (MEM_WB_valid)
            total_instructions <= total_instructions + 1;
        if (total_cycles > 0)
            ipc_x100 <= (total_instructions * 100) / total_cycles;
    end
end

endmodule

p1_ipc_tracker/tb_pipeline.v
`timescale 1ns/1ps

module tb_pipeline;
    reg         clk = 0, rst = 1;
    reg  [31:0] instruction;
    wire [63:0] ipc_x100, total_instr, total_cycles, stall_cyc;

    integer i, wl;
    reg [31:0] prog [0:2][0:31];
    integer pc;

    pipeline_cpu dut (
        .clk(clk), .rst(rst),
        .instruction(instruction),
        .ipc_x100(ipc_x100),
        .total_instructions(total_instr),
        .total_cycles(total_cycles),
        .stall_cycles(stall_cyc)
    );

    always #5 clk = ~clk;

    initial begin
        $dumpfile("pipeline.vcd");
        $dumpvars(0, tb_pipeline);

        for (i=0; i<32; i=i+1)
            prog[0][i] = {3'b000, 5'd1, 5'd2, 5'd3, 14'b0};

        for (i=0; i<32; i=i+1) begin
            if (i%3 == 2)
                prog[1][i] = {3'b110, 29'b0};
            else
                prog[1][i] = {3'b000, 5'd1, 5'd2, 5'd3, 14'b0};
        end

        for (i=0; i<32; i=i+2) begin
            prog[2][i]   = {3'b001, 5'd1, 5'd2, 5'd4, 14'b0};
            prog[2][i+1] = {3'b000, 5'd4, 5'd2, 5'd5, 14'b0};
        end

        for (wl=0; wl<3; wl=wl+1) begin
            rst = 1; pc = 0;
            repeat(3) @(posedge clk);
            rst = 0;

            for (i=0; i<60; i=i+1) begin
                instruction = prog[wl][pc % 32];
                pc = pc + 1;
                @(posedge clk);
            end

            instruction = 32'b0;
            repeat(5) @(posedge clk);

            $display("WL%0d CYCLES=%0d INSTRS=%0d STALLS=%0d IPC_X100=%0d",
                     wl, total_cycles, total_instr, stall_cyc, ipc_x100);
        end

        $finish;
    end
endmodule

p1_ipc_tracker/pipeline.vcd
$date
	Thu May 28 06:19:48 2026
$end
$version
	Icarus Verilog
$end
$timescale
	1ps
$end
$scope module tb_pipeline $end
$var wire 64 ! total_instr [63:0] $end
$var wire 64 " total_cycles [63:0] $end
$var wire 64 # stall_cyc [63:0] $end
$var wire 64 $ ipc_x100 [63:0] $end
$var reg 1 % clk $end
$var reg 32 & instruction [31:0] $end
$var reg 1 ' rst $end
$var integer 32 ( i [31:0] $end
$var integer 32 ) pc [31:0] $end
$var integer 32 * wl [31:0] $end
$scope module dut $end
$var wire 1 + branch_taken $end
$var wire 1 % clk $end
$var wire 32 , instruction [31:0] $end
$var wire 1 ' rst $end
$var wire 1 - stall $end
$var wire 5 . rs2 [4:0] $end
$var wire 5 / rs1 [4:0] $end
$var wire 5 0 rd_mem [4:0] $end
$var wire 5 1 rd_ex [4:0] $end
$var wire 3 2 opcode [2:0] $end
$var reg 32 3 EX_MEM_instr [31:0] $end
$var reg 1 4 EX_MEM_valid $end
$var reg 32 5 ID_EX_instr [31:0] $end
$var reg 1 6 ID_EX_valid $end
$var reg 32 7 IF_ID_instr [31:0] $end
$var reg 1 8 IF_ID_valid $end
$var reg 32 9 MEM_WB_instr [31:0] $end
$var reg 1 : MEM_WB_valid $end
$var reg 64 ; ipc_x100 [63:0] $end
$var reg 64 < stall_cycles [63:0] $end
$var reg 64 = total_cycles [63:0] $end
$var reg 64 > total_instructions [63:0] $end
$upscope $end
$upscope $end
$enddefinitions $end
$comment Show the parameter values. $end
$dumpall
$end
#0
$dumpvars
bx >
bx =
bx <
bx ;
x:
bx 9
x8
bx 7
x6
bx 5
x4
bx 3
bx 2
bx 1
bx 0
bx /
bx .
x-
bx ,
x+
b0 *
b0 )
b100000 (
1'
bx &
0%
bx $
bx #
bx "
bx !
$end
#5000
0-
b0 0
0+
b0 1
b0 2
b0 /
b0 .
0:
b0 9
04
b0 3
06
b0 5
08
b0 7
b0 $
b0 ;
b0 #
b0 <
b0 !
b0 >
b0 "
b0 =
1%
#10000
0%
#15000
1%
#20000
0%
#25000
b1 /
b10 .
18
b1000100001100000000000000 7
b1 "
b1 =
b1 )
b1000100001100000000000000 &
b1000100001100000000000000 ,
b0 (
0'
1%
#30000
0%
#35000
b11 1
b10 "
b10 =
16
b1000100001100000000000000 5
b10 )
b1 (
1%
#40000
0%
#45000
b11 0
14
b1000100001100000000000000 3
b11 "
b11 =
b11 )
b10 (
1%
#50000
0%
#55000
b100 "
b100 =
1:
b1000100001100000000000000 9
b100 )
b11 (
1%
#60000
0%
#65000
b1 !
b1 >
b101 "
b101 =
b101 )
b100 (
1%
#70000
0%
#75000
b10100 $
b10100 ;
b10 !
b10 >
b110 "
b110 =
b110 )
b101 (
1%
#80000
0%
#85000
b100001 $
b100001 ;
b11 !
b11 >
b111 "
b111 =
b111 )
b110 (
1%
#90000
0%
#95000
b101010 $
b101010 ;
b100 !
b100 >
b1000 "
b1000 =
b1000 )
b111 (
1%
#100000
0%
#105000
b110010 $
b110010 ;
b101 !
b101 >
b1001 "
b1001 =
b1001 )
b1000 (
1%
#110000
0%
#115000
b110111 $
b110111 ;
b110 !
b110 >
b1010 "
b1010 =
b1010 )
b1001 (
1%
#120000
0%
#125000
b111100 $
b111100 ;
b111 !
b111 >
b1011 "
b1011 =
b1011 )
b1010 (
1%
#130000
0%
#135000
b111111 $
b111111 ;
b1000 !
b1000 >
b1100 "
b1100 =
b1100 )
b1011 (
1%
#140000
0%
#145000
b1000010 $
b1000010 ;
b1001 !
b1001 >
b1101 "
b1101 =
b1101 )
b1100 (
1%
#150000
0%
#155000
b1000101 $
b1000101 ;
b1010 !
b1010 >
b1110 "
b1110 =
b1110 )
b1101 (
1%
#160000
0%
#165000
b1000111 $
b1000111 ;
b1011 !
b1011 >
b1111 "
b1111 =
b1111 )
b1110 (
1%
#170000
0%
#175000
b1001001 $
b1001001 ;
b1100 !
b1100 >
b10000 "
b10000 =
b10000 )
b1111 (
1%
#180000
0%
#185000
b1001011 $
b1001011 ;
b1101 !
b1101 >
b10001 "
b10001 =
b10001 )
b10000 (
1%
#190000
0%
#195000
b1001100 $
b1001100 ;
b1110 !
b1110 >
b10010 "
b10010 =
b10010 )
b10001 (
1%
#200000
0%
#205000
b1001101 $
b1001101 ;
b1111 !
b1111 >
b10011 "
b10011 =
b10011 )
b10010 (
1%
#210000
0%
#215000
b1001110 $
b1001110 ;
b10000 !
b10000 >
b10100 "
b10100 =
b10100 )
b10011 (
1%
#220000
0%
#225000
b1010000 $
b1010000 ;
b10001 !
b10001 >
b10101 "
b10101 =
b10101 )
b10100 (
1%
#230000
0%
#235000
b10010 !
b10010 >
b10110 "
b10110 =
b10110 )
b10101 (
1%
#240000
0%
#245000
b1010001 $
b1010001 ;
b10011 !
b10011 >
b10111 "
b10111 =
b10111 )
b10110 (
1%
#250000
0%
#255000
b1010010 $
b1010010 ;
b10100 !
b10100 >
b11000 "
b11000 =
b11000 )
b10111 (
1%
#260000
0%
#265000
b1010011 $
b1010011 ;
b10101 !
b10101 >
b11001 "
b11001 =
b11001 )
b11000 (
1%
#270000
0%
#275000
b1010100 $
b1010100 ;
b10110 !
b10110 >
b11010 "
b11010 =
b11010 )
b11001 (
1%
#280000
0%
#285000
b10111 !
b10111 >
b11011 "
b11011 =
b11011 )
b11010 (
1%
#290000
0%
#295000
b1010101 $
b1010101 ;
b11000 !
b11000 >
b11100 "
b11100 =
b11100 )
b11011 (
1%
#300000
0%
#305000
b11001 !
b11001 >
b11101 "
b11101 =
b11101 )
b11100 (
1%
#310000
0%
#315000
b1010110 $
b1010110 ;
b11010 !
b11010 >
b11110 "
b11110 =
b11110 )
b11101 (
1%
#320000
0%
#325000
b11011 !
b11011 >
b11111 "
b11111 =
b11111 )
b11110 (
1%
#330000
0%
#335000
b1010111 $
b1010111 ;
b11100 !
b11100 >
b100000 "
b100000 =
b100000 )
b11111 (
1%
#340000
0%
#345000
b11101 !
b11101 >
b100001 "
b100001 =
b100001 )
b100000 (
1%
#350000
0%
#355000
b11110 !
b11110 >
b100010 "
b100010 =
b100010 )
b100001 (
1%
#360000
0%
#365000
b1011000 $
b1011000 ;
b11111 !
b11111 >
b100011 "
b100011 =
b100011 )
b100010 (
1%
#370000
0%
#375000
b100000 !
b100000 >
b100100 "
b100100 =
b100100 )
b100011 (
1%
#380000
0%
#385000
b100001 !
b100001 >
b100101 "
b100101 =
b100101 )
b100100 (
1%
#390000
0%
#395000
b1011001 $
b1011001 ;
b100010 !
b100010 >
b100110 "
b100110 =
b100110 )
b100101 (
1%
#400000
0%
#405000
b100011 !
b100011 >
b100111 "
b100111 =
b100111 )
b100110 (
1%
#410000
0%
#415000
b100100 !
b100100 >
b101000 "
b101000 =
b101000 )
b100111 (
1%
#420000
0%
#425000
b1011010 $
b1011010 ;
b100101 !
b100101 >
b101001 "
b101001 =
b101001 )
b101000 (
1%
#430000
0%
#435000
b100110 !
b100110 >
b101010 "
b101010 =
b101010 )
b101001 (
1%
#440000
0%
#445000
b100111 !
b100111 >
b101011 "
b101011 =
b101011 )
b101010 (
1%
#450000
0%
#455000
b101000 !
b101000 >
b101100 "
b101100 =
b101100 )
b101011 (
1%
#460000
0%
#465000
b101001 !
b101001 >
b101101 "
b101101 =
b101101 )
b101100 (
1%
#470000
0%
#475000
b1011011 $
b1011011 ;
b101010 !
b101010 >
b101110 "
b101110 =
b101110 )
b101101 (
1%
#480000
0%
#485000
b101011 !
b101011 >
b101111 "
b101111 =
b101111 )
b101110 (
1%
#490000
0%
#495000
b101100 !
b101100 >
b110000 "
b110000 =
b110000 )
b101111 (
1%
#500000
0%
#505000
b101101 !
b101101 >
b110001 "
b110001 =
b110001 )
b110000 (
1%
#510000
0%
#515000
b101110 !
b101110 >
b110010 "
b110010 =
b110010 )
b110001 (
1%
#520000
0%
#525000
b1011100 $
b1011100 ;
b101111 !
b101111 >
b110011 "
b110011 =
b110011 )
b110010 (
1%
#530000
0%
#535000
b110000 !
b110000 >
b110100 "
b110100 =
b110100 )
b110011 (
1%
#540000
0%
#545000
b110001 !
b110001 >
b110101 "
b110101 =
b110101 )
b110100 (
1%
#550000
0%
#555000
b110010 !
b110010 >
b110110 "
b110110 =
b110110 )
b110101 (
1%
#560000
0%
#565000
b110011 !
b110011 >
b110111 "
b110111 =
b110111 )
b110110 (
1%
#570000
0%
#575000
b110100 !
b110100 >
b111000 "
b111000 =
b111000 )
b110111 (
1%
#580000
0%
#585000
b110101 !
b110101 >
b111001 "
b111001 =
b111001 )
b111000 (
1%
#590000
0%
#595000
b110110 !
b110110 >
b111010 "
b111010 =
b111010 )
b111001 (
1%
#600000
0%
#605000
b1011101 $
b1011101 ;
b110111 !
b110111 >
b111011 "
b111011 =
b111011 )
b111010 (
1%
#610000
0%
#615000
b111000 !
b111000 >
b111100 "
b111100 =
b111100 )
b111011 (
1%
#620000
0%
#625000
b0 /
b0 .
b0 7
b111001 !
b111001 >
b111101 "
b111101 =
b0 &
b0 ,
b111100 (
1%
#630000
0%
#635000
b0 1
b111010 !
b111010 >
b111110 "
b111110 =
b0 5
1%
#640000
0%
#645000
b0 0
b0 3
b111011 !
b111011 >
b111111 "
b111111 =
1%
#650000
0%
#655000
b111100 !
b111100 >
b1000000 "
b1000000 =
b0 9
1%
#660000
0%
#665000
b111101 !
b111101 >
b1000001 "
b1000001 =
1%
#670000
0%
#675000
b0 $
b0 ;
b0 !
b0 >
b0 "
b0 =
0:
04
06
08
b0 )
1'
b1 *
1%
#680000
0%
#685000
1%
#690000
0%
#695000
1%
#700000
0%
#705000
b1 /
b10 .
18
b1000100001100000000000000 7
b1 "
b1 =
b1 )
b1000100001100000000000000 &
b1000100001100000000000000 ,
b0 (
0'
1%
#710000
0%
#715000
b11 1
b10 "
b10 =
16
b1000100001100000000000000 5
b10 )
b1 (
1%
#720000
0%
#725000
b11 0
b110 2
b0 /
b0 .
14
b1000100001100000000000000 3
b11000000000000000000000000000000 7
b11 "
b11 =
b11 )
b11000000000000000000000000000000 &
b11000000000000000000000000000000 ,
b10 (
1%
#730000
0%
#735000
1+
b0 1
b0 2
b1 /
b10 .
b100 "
b100 =
1:
b1000100001100000000000000 9
b11000000000000000000000000000000 5
b1000100001100000000000000 7
b100 )
b1000100001100000000000000 &
b1000100001100000000000000 ,
b11 (
1%
#740000
0%
#745000
0+
b0 0
b11 1
b0 /
b0 .
b11000000000000000000000000000000 3
b1000100001100000000000000 5
08
b0 7
b1 !
b1 >
b101 "
b101 =
b101 )
b100 (
1%
#750000
0%
#755000
b11 0
b0 1
b110 2
b10100 $
b10100 ;
b10 !
b10 >
b110 "
b110 =
b11000000000000000000000000000000 9
b1000100001100000000000000 3
06
b0 5
18
b11000000000000000000000000000000 7
b110 )
b11000000000000000000000000000000 &
b11000000000000000000000000000000 ,
b101 (
1%
#760000
0%
#765000
b0 0
1+
b0 2
b1 /
b10 .
b1000100001100000000000000 9
04
b0 3
16
b11000000000000000000000000000000 5
b1000100001100000000000000 7
b100001 $
b100001 ;
b11 !
b11 >
b111 "
b111 =
b111 )
b1000100001100000000000000 &
b1000100001100000000000000 ,
b110 (
1%
#770000
0%
#775000
0+
b11 1
b0 /
b0 .
b101010 $
b101010 ;
b100 !
b100 >
b1000 "
b1000 =
0:
b0 9
14
b11000000000000000000000000000000 3
b1000100001100000000000000 5
08
b0 7
b1000 )
b111 (
1%
#780000
0%
#785000
b11 0
b0 1
b110 2
1:
b11000000000000000000000000000000 9
b1000100001100000000000000 3
06
b0 5
18
b11000000000000000000000000000000 7
b110010 $
b110010 ;
b1001 "
b1001 =
b1001 )
b11000000000000000000000000000000 &
b11000000000000000000000000000000 ,
b1000 (
1%
#790000
0%
#795000
b0 0
1+
b0 2
b1 /
b10 .
b101100 $
b101100 ;
b101 !
b101 >
b1010 "
b1010 =
b1000100001100000000000000 9
04
b0 3
16
b11000000000000000000000000000000 5
b1000100001100000000000000 7
b1010 )
b1000100001100000000000000 &
b1000100001100000000000000 ,
b1001 (
1%
#800000
0%
#805000
0+
b11 1
b0 /
b0 .
0:
b0 9
14
b11000000000000000000000000000000 3
b1000100001100000000000000 5
08
b0 7
b110010 $
b110010 ;
b110 !
b110 >
b1011 "
b1011 =
b1011 )
b1010 (
1%
#810000
0%
#815000
b11 0
b0 1
b110 2
b110110 $
b110110 ;
b1100 "
b1100 =
1:
b11000000000000000000000000000000 9
b1000100001100000000000000 3
06
b0 5
18
b11000000000000000000000000000000 7
b1100 )
b11000000000000000000000000000000 &
b11000000000000000000000000000000 ,
b1011 (
1%
#820000
0%
#825000
b0 0
1+
b0 2
b1 /
b10 .
b1000100001100000000000000 9
04
b0 3
16
b11000000000000000000000000000000 5
b1000100001100000000000000 7
b110010 $
b110010 ;
b111 !
b111 >
b1101 "
b1101 =
b1101 )
b1000100001100000000000000 &
b1000100001100000000000000 ,
b1100 (
1%
#830000
0%
#835000
0+
b11 1
b0 /
b0 .
b110101 $
b110101 ;
b1000 !
b1000 >
b1110 "
b1110 =
0:
b0 9
14
b11000000000000000000000000000000 3
b1000100001100000000000000 5
08
b0 7
b1110 )
b1101 (
1%
#840000
0%
#845000
b11 0
b0 1
b110 2
1:
b11000000000000000000000000000000 9
b1000100001100000000000000 3
06
b0 5
18
b11000000000000000000000000000000 7
b111001 $
b111001 ;
b1111 "
b1111 =
b1111 )
b11000000000000000000000000000000 &
b11000000000000000000000000000000 ,
b1110 (
1%
#850000
0%
#855000
b0 0
1+
b0 2
b1 /
b10 .
b110101 $
b110101 ;
b1001 !
b1001 >
b10000 "
b10000 =
b1000100001100000000000000 9
04
b0 3
16
b11000000000000000000000000000000 5
b1000100001100000000000000 7
b10000 )
b1000100001100000000000000 &
b1000100001100000000000000 ,
b1111 (
1%
#860000
0%
#865000
0+
b11 1
b0 /
b0 .
0:
b0 9
14
b11000000000000000000000000000000 3
b1000100001100000000000000 5
08
b0 7
b111000 $
b111000 ;
b1010 !
b1010 >
b10001 "
b10001 =
b10001 )
b10000 (
1%
#870000
0%
#875000
b11 0
b0 1
b110 2
b111010 $
b111010 ;
b10010 "
b10010 =
1:
b11000000000000000000000000000000 9
b1000100001100000000000000 3
06
b0 5
18
b11000000000000000000000000000000 7
b10010 )
b11000000000000000000000000000000 &
b11000000000000000000000000000000 ,
b10001 (
1%
#880000
0%
#885000
b0 0
1+
b0 2
b1 /
b10 .
b1000100001100000000000000 9
04
b0 3
16
b11000000000000000000000000000000 5
b1000100001100000000000000 7
b110111 $
b110111 ;
b1011 !
b1011 >
b10011 "
b10011 =
b10011 )
b1000100001100000000000000 &
b1000100001100000000000000 ,
b10010 (
1%
#890000
0%
#895000
0+
b11 1
b0 /
b0 .
b111001 $
b111001 ;
b1100 !
b1100 >
b10100 "
b10100 =
0:
b0 9
14
b11000000000000000000000000000000 3
b1000100001100000000000000 5
08
b0 7
b10100 )
b10011 (
1%
#900000
0%
#905000
b11 0
b0 1
b110 2
1:
b11000000000000000000000000000000 9
b1000100001100000000000000 3
06
b0 5
18
b11000000000000000000000000000000 7
b111100 $
b111100 ;
b10101 "
b10101 =
b10101 )
b11000000000000000000000000000000 &
b11000000000000000000000000000000 ,
b10100 (
1%
#910000
0%
#915000
b0 0
1+
b0 2
b1 /
b10 .
b111001 $
b111001 ;
b1101 !
b1101 >
b10110 "
b10110 =
b1000100001100000000000000 9
04
b0 3
16
b11000000000000000000000000000000 5
b1000100001100000000000000 7
b10110 )
b1000100001100000000000000 &
b1000100001100000000000000 ,
b10101 (
1%
#920000
0%
#925000
0+
b11 1
b0 /
b0 .
0:
b0 9
14
b11000000000000000000000000000000 3
b1000100001100000000000000 5
08
b0 7
b111011 $
b111011 ;
b1110 !
b1110 >
b10111 "
b10111 =
b10111 )
b10110 (
1%
#930000
0%
#935000
b11 0
b0 1
b110 2
b111100 $
b111100 ;
b11000 "
b11000 =
1:
b11000000000000000000000000000000 9
b1000100001100000000000000 3
06
b0 5
18
b11000000000000000000000000000000 7
b11000 )
b11000000000000000000000000000000 &
b11000000000000000000000000000000 ,
b10111 (
1%
#940000
0%
#945000
b0 0
1+
b0 2
b1 /
b10 .
b1000100001100000000000000 9
04
b0 3
16
b11000000000000000000000000000000 5
b1000100001100000000000000 7
b111010 $
b111010 ;
b1111 !
b1111 >
b11001 "
b11001 =
b11001 )
b1000100001100000000000000 &
b1000100001100000000000000 ,
b11000 (
1%
#950000
0%
#955000
0+
b11 1
b0 /
b0 .
b111100 $
b111100 ;
b10000 !
b10000 >
b11010 "
b11010 =
0:
b0 9
14
b11000000000000000000000000000000 3
b1000100001100000000000000 5
08
b0 7
b11010 )
b11001 (
1%
#960000
0%
#965000
b11 0
b0 1
b110 2
1:
b11000000000000000000000000000000 9
b1000100001100000000000000 3
06
b0 5
18
b11000000000000000000000000000000 7
b111101 $
b111101 ;
b11011 "
b11011 =
b11011 )
b11000000000000000000000000000000 &
b11000000000000000000000000000000 ,
b11010 (
1%
#970000
0%
#975000
b0 0
1+
b0 2
b1 /
b10 .
b111011 $
b111011 ;
b10001 !
b10001 >
b11100 "
b11100 =
b1000100001100000000000000 9
04
b0 3
16
b11000000000000000000000000000000 5
b1000100001100000000000000 7
b11100 )
b1000100001100000000000000 &
b1000100001100000000000000 ,
b11011 (
1%
#980000
0%
#985000
0+
b11 1
b0 /
b0 .
0:
b0 9
14
b11000000000000000000000000000000 3
b1000100001100000000000000 5
08
b0 7
b111100 $
b111100 ;
b10010 !
b10010 >
b11101 "
b11101 =
b11101 )
b11100 (
1%
#990000
0%
#995000
b11 0
b0 1
b110 2
b111110 $
b111110 ;
b11110 "
b11110 =
1:
b11000000000000000000000000000000 9
b1000100001100000000000000 3
06
b0 5
18
b11000000000000000000000000000000 7
b11110 )
b11000000000000000000000000000000 &
b11000000000000000000000000000000 ,
b11101 (
1%
#1000000
0%
#1005000
b0 0
1+
b0 2
b1 /
b10 .
b1000100001100000000000000 9
04
b0 3
16
b11000000000000000000000000000000 5
b1000100001100000000000000 7
b111100 $
b111100 ;
b10011 !
b10011 >
b11111 "
b11111 =
b11111 )
b1000100001100000000000000 &
b1000100001100000000000000 ,
b11110 (
1%
#1010000
0%
#1015000
0+
b11 1
b0 /
b0 .
b111101 $
b111101 ;
b10100 !
b10100 >
b100000 "
b100000 =
0:
b0 9
14
b11000000000000000000000000000000 3
b1000100001100000000000000 5
08
b0 7
b100000 )
b11111 (
1%
#1020000
0%
#1025000
b11 0
b0 1
b1 /
b10 .
1:
b11000000000000000000000000000000 9
b1000100001100000000000000 3
06
b0 5
18
b1000100001100000000000000 7
b111110 $
b111110 ;
b100001 "
b100001 =
b100001 )
b100000 (
1%
#1030000
0%
#1035000
b0 0
b11 1
b111100 $
b111100 ;
b10101 !
b10101 >
b100010 "
b100010 =
b1000100001100000000000000 9
04
b0 3
16
b1000100001100000000000000 5
b100010 )
b100001 (
1%
#1040000
0%
#1045000
b11 0
b110 2
b0 /
b0 .
0:
b0 9
14
b1000100001100000000000000 3
b11000000000000000000000000000000 7
b111101 $
b111101 ;
b10110 !
b10110 >
b100011 "
b100011 =
b100011 )
b11000000000000000000000000000000 &
b11000000000000000000000000000000 ,
b100010 (
1%
#1050000
0%
#1055000
1+
b0 1
b0 2
b1 /
b10 .
b111110 $
b111110 ;
b100100 "
b100100 =
1:
b1000100001100000000000000 9
b11000000000000000000000000000000 5
b1000100001100000000000000 7
b100100 )
b1000100001100000000000000 &
b1000100001100000000000000 ,
b100011 (
1%
#1060000
0%
#1065000
0+
b0 0
b11 1
b0 /
b0 .
b11000000000000000000000000000000 3
b1000100001100000000000000 5
08
b0 7
b111101 $
b111101 ;
b10111 !
b10111 >
b100101 "
b100101 =
b100101 )
b100100 (
1%
#1070000
0%
#1075000
b11 0
b0 1
b110 2
b111110 $
b111110 ;
b11000 !
b11000 >
b100110 "
b100110 =
b11000000000000000000000000000000 9
b1000100001100000000000000 3
06
b0 5
18
b11000000000000000000000000000000 7
b100110 )
b11000000000000000000000000000000 &
b11000000000000000000000000000000 ,
b100101 (
1%
#1080000
0%
#1085000
b0 0
1+
b0 2
b1 /
b10 .
b1000100001100000000000000 9
04
b0 3
16
b11000000000000000000000000000000 5
b1000100001100000000000000 7
b111111 $
b111111 ;
b11001 !
b11001 >
b100111 "
b100111 =
b100111 )
b1000100001100000000000000 &
b1000100001100000000000000 ,
b100110 (
1%
#1090000
0%
#1095000
0+
b11 1
b0 /
b0 .
b1000000 $
b1000000 ;
b11010 !
b11010 >
b101000 "
b101000 =
0:
b0 9
14
b11000000000000000000000000000000 3
b1000100001100000000000000 5
08
b0 7
b101000 )
b100111 (
1%
#1100000
0%
#1105000
b11 0
b0 1
b110 2
1:
b11000000000000000000000000000000 9
b1000100001100000000000000 3
06
b0 5
18
b11000000000000000000000000000000 7
b1000001 $
b1000001 ;
b101001 "
b101001 =
b101001 )
b11000000000000000000000000000000 &
b11000000000000000000000000000000 ,
b101000 (
1%
#1110000
0%
#1115000
b0 0
1+
b0 2
b1 /
b10 .
b111111 $
b111111 ;
b11011 !
b11011 >
b101010 "
b101010 =
b1000100001100000000000000 9
04
b0 3
16
b11000000000000000000000000000000 5
b1000100001100000000000000 7
b101010 )
b1000100001100000000000000 &
b1000100001100000000000000 ,
b101001 (
1%
#1120000
0%
#1125000
0+
b11 1
b0 /
b0 .
0:
b0 9
14
b11000000000000000000000000000000 3
b1000100001100000000000000 5
08
b0 7
b1000000 $
b1000000 ;
b11100 !
b11100 >
b101011 "
b101011 =
b101011 )
b101010 (
1%
#1130000
0%
#1135000
b11 0
b0 1
b110 2
b1000001 $
b1000001 ;
b101100 "
b101100 =
1:
b11000000000000000000000000000000 9
b1000100001100000000000000 3
06
b0 5
18
b11000000000000000000000000000000 7
b101100 )
b11000000000000000000000000000000 &
b11000000000000000000000000000000 ,
b101011 (
1%
#1140000
0%
#1145000
b0 0
1+
b0 2
b1 /
b10 .
b1000100001100000000000000 9
04
b0 3
16
b11000000000000000000000000000000 5
b1000100001100000000000000 7
b111111 $
b111111 ;
b11101 !
b11101 >
b101101 "
b101101 =
b101101 )
b1000100001100000000000000 &
b1000100001100000000000000 ,
b101100 (
1%
#1150000
0%
#1155000
0+
b11 1
b0 /
b0 .
b1000000 $
b1000000 ;
b11110 !
b11110 >
b101110 "
b101110 =
0:
b0 9
14
b11000000000000000000000000000000 3
b1000100001100000000000000 5
08
b0 7
b101110 )
b101101 (
1%
#1160000
0%
#1165000
b11 0
b0 1
b110 2
1:
b11000000000000000000000000000000 9
b1000100001100000000000000 3
06
b0 5
18
b11000000000000000000000000000000 7
b1000001 $
b1000001 ;
b101111 "
b101111 =
b101111 )
b11000000000000000000000000000000 &
b11000000000000000000000000000000 ,
b101110 (
1%
#1170000
0%
#1175000
b0 0
1+
b0 2
b1 /
b10 .
b111111 $
b111111 ;
b11111 !
b11111 >
b110000 "
b110000 =
b1000100001100000000000000 9
04
b0 3
16
b11000000000000000000000000000000 5
b1000100001100000000000000 7
b110000 )
b1000100001100000000000000 &
b1000100001100000000000000 ,
b101111 (
1%
#1180000
0%
#1185000
0+
b11 1
b0 /
b0 .
0:
b0 9
14
b11000000000000000000000000000000 3
b1000100001100000000000000 5
08
b0 7
b1000000 $
b1000000 ;
b100000 !
b100000 >
b110001 "
b110001 =
b110001 )
b110000 (
1%
#1190000
0%
#1195000
b11 0
b0 1
b110 2
b1000001 $
b1000001 ;
b110010 "
b110010 =
1:
b11000000000000000000000000000000 9
b1000100001100000000000000 3
06
b0 5
18
b11000000000000000000000000000000 7
b110010 )
b11000000000000000000000000000000 &
b11000000000000000000000000000000 ,
b110001 (
1%
#1200000
0%
#1205000
b0 0
1+
b0 2
b1 /
b10 .
b1000100001100000000000000 9
04
b0 3
16
b11000000000000000000000000000000 5
b1000100001100000000000000 7
b1000000 $
b1000000 ;
b100001 !
b100001 >
b110011 "
b110011 =
b110011 )
b1000100001100000000000000 &
b1000100001100000000000000 ,
b110010 (
1%
#1210000
0%
#1215000
0+
b11 1
b0 /
b0 .
b100010 !
b100010 >
b110100 "
b110100 =
0:
b0 9
14
b11000000000000000000000000000000 3
b1000100001100000000000000 5
08
b0 7
b110100 )
b110011 (
1%
#1220000
0%
#1225000
b11 0
b0 1
b110 2
1:
b11000000000000000000000000000000 9
b1000100001100000000000000 3
06
b0 5
18
b11000000000000000000000000000000 7
b1000001 $
b1000001 ;
b110101 "
b110101 =
b110101 )
b11000000000000000000000000000000 &
b11000000000000000000000000000000 ,
b110100 (
1%
#1230000
0%
#1235000
b0 0
1+
b0 2
b1 /
b10 .
b1000000 $
b1000000 ;
b100011 !
b100011 >
b110110 "
b110110 =
b1000100001100000000000000 9
04
b0 3
16
b11000000000000000000000000000000 5
b1000100001100000000000000 7
b110110 )
b1000100001100000000000000 &
b1000100001100000000000000 ,
b110101 (
1%
#1240000
0%
#1245000
0+
b11 1
b0 /
b0 .
0:
b0 9
14
b11000000000000000000000000000000 3
b1000100001100000000000000 5
08
b0 7
b100100 !
b100100 >
b110111 "
b110111 =
b110111 )
b110110 (
1%
#1250000
0%
#1255000
b11 0
b0 1
b110 2
b1000001 $
b1000001 ;
b111000 "
b111000 =
1:
b11000000000000000000000000000000 9
b1000100001100000000000000 3
06
b0 5
18
b11000000000000000000000000000000 7
b111000 )
b11000000000000000000000000000000 &
b11000000000000000000000000000000 ,
b110111 (
1%
#1260000
0%
#1265000
b0 0
1+
b0 2
b1 /
b10 .
b1000100001100000000000000 9
04
b0 3
16
b11000000000000000000000000000000 5
b1000100001100000000000000 7
b1000000 $
b1000000 ;
b100101 !
b100101 >
b111001 "
b111001 =
b111001 )
b1000100001100000000000000 &
b1000100001100000000000000 ,
b111000 (
1%
#1270000
0%
